pawdf/__init__.py
pawdf/array_pdf/WEBTEST.PY
pawdf/array_pdf/__init__.py
pawdf/array_pdf/addmenu.py
pawdf/array_pdf/array_cm.py
pawdf/array_pdf/array_p.py
pawdf/array_pdf/removemenu.py
pawdf/array_pdf/tresting.py
pawdf-0.1.0.dist-info/WHEEL
pawdf-0.1.0.dist-info/entry_points.txt
pawdf-0.1.0.dist-info/METADATA
pawdf-0.1.0.dist-info/RECORD
