Metadata-Version: 2.3
Name: pawdf
Version: 0.1.0
Summary: pdf tools
Author: PawRequest
Author-email: PawRequest <pawdf+pawrequest@users.noreply.github.com>
Requires-Dist: pypdf
Requires-Dist: context-menu ; extra == 'cmenu'
Requires-Python: >=3.12
Provides-Extra: cmenu
